libosrmpy/__init__.py
libosrmpy/_libosrmpy.cpython-312-x86_64-linux-gnu.so
libosrmpy/engine.py
libosrmpy/schema.py
libosrmpy.libs/libboost_iostreams-f820f73d.so.1.74.0
libosrmpy.libs/libboost_thread-41c8fe93.so.1.74.0
libosrmpy.libs/libbz2-5e516f77.so.1.0.4
libosrmpy.libs/liblzma-493cb401.so.5.2.5
libosrmpy.libs/libzstd-5df4f4df.so.1.4.8
libosrmpy-0.1.0.dist-info/METADATA
libosrmpy-0.1.0.dist-info/WHEEL
libosrmpy-0.1.0.dist-info/RECORD
libosrmpy-0.1.0.dist-info/sboms/auditwheel.cdx.json
