Metadata-Version: 2.2
Name: libosrmpy
Version: 0.1.0
Summary: Python bindings for libosrm using pybind11
Author-Email: huiseomKimML <huiseom.kim@meshkorea.net>
Requires-Python: >=3.12
Requires-Dist: numpy>=2.3.5
